mwoauth/__init__.py
mwoauth/about.py
mwoauth/defaults.py
mwoauth/errors.py
mwoauth/flask.py
mwoauth/functions.py
mwoauth/handshaker.py
mwoauth/tokens.py
mwoauth/tests/__init__.py
mwoauth/tests/test_functions.py
mwoauth-0.4.0.dist-info/LICENSE
mwoauth-0.4.0.dist-info/METADATA
mwoauth-0.4.0.dist-info/WHEEL
mwoauth-0.4.0.dist-info/top_level.txt
mwoauth-0.4.0.dist-info/RECORD
