Metadata-Version: 2.1
Name: mwoauth
Version: 0.4.0
Summary: A generic MediaWiki OAuth handshake helper.
Home-page: https://github.com/mediawiki-utilities/python-mwoauth
Author: Aaron Halfaker / Filippo Valsorda
Author-email: aaron.halfaker@gmail.com
License: MIT
Platform: UNKNOWN
Classifier: Development Status :: 4 - Beta
Classifier: Topic :: Security
Classifier: License :: OSI Approved :: MIT License
Classifier: Topic :: Software Development :: Libraries :: Python Modules
Requires-Dist: PyJWT >=1.0.1
Requires-Dist: oauthlib
Requires-Dist: requests
Requires-Dist: requests-oauthlib
Provides-Extra: flask
Requires-Dist: flask ; extra == 'flask'
